eugeroic/__init__.py
eugeroic/__main__.py
eugeroic/cli.py
eugeroic/decorator.py
eugeroic/version.py
eugeroic/drivers/__init__.py
eugeroic/drivers/linux/__init__.py
eugeroic/drivers/linux/bus.py
eugeroic/drivers/linux/driver.py
eugeroic/drivers/macos/__init__.py
eugeroic/drivers/macos/cfstringref.py
eugeroic/drivers/macos/driver.py
eugeroic/drivers/macos/iokit.py
eugeroic/drivers/null/__init__.py
eugeroic/drivers/null/driver.py
eugeroic/drivers/windows/__init__.py
eugeroic/drivers/windows/display.py
eugeroic/drivers/windows/driver.py
eugeroic-1.8.2.dist-info/LICENSE.txt
eugeroic-1.8.2.dist-info/METADATA
eugeroic-1.8.2.dist-info/WHEEL
eugeroic-1.8.2.dist-info/top_level.txt
eugeroic-1.8.2.dist-info/zip-safe
eugeroic-1.8.2.dist-info/RECORD
