Metadata-Version: 2.1
Name: eugeroic
Version: 1.8.2
Summary: Prevent your computer from sleeping
Home-page: https://github.com/sixty-north/eugeroic
Author: Sixty North AS
Author-email: systems+eugeroic@sixty-north.com
License: MIT License
Keywords: macos sleep
Classifier: Development Status :: 3 - Alpha
Classifier: Intended Audience :: Developers
Classifier: Topic :: Software Development :: Libraries :: Python Modules
Classifier: License :: OSI Approved :: MIT License
Classifier: Programming Language :: Python :: 3 :: Only
Classifier: Programming Language :: Python :: 3.11
License-File: LICENSE.txt
Requires-Dist: pyobjc-framework-Cocoa >=9.2 ; platform_system == "Darwin"
Requires-Dist: dbus-next >=0.2.3 ; platform_system == "Linux"
Requires-Dist: backports.strenum >=1.1.1 ; python_version < "3.11"
Provides-Extra: dev
Requires-Dist: bumpversion ; extra == 'dev'
Provides-Extra: doc
Requires-Dist: sphinx ; extra == 'doc'
Requires-Dist: sphinx-rtd-theme ; extra == 'doc'
Requires-Dist: better-apidoc ; extra == 'doc'
Provides-Extra: test
Requires-Dist: pytest ; extra == 'test'
Requires-Dist: coverage ; extra == 'test'
Requires-Dist: pytest-cov ; extra == 'test'
Requires-Dist: hypothesis ; extra == 'test'
Requires-Dist: tox ; extra == 'test'
